[
  {
    "name": "theme_info",
    "theme_name": "One Half Coffee - Minimal",
    "theme_version": "1.0.0",
    "theme_author": "AI Studio",
    "theme_documentation_url": "https://www.onehalfcoffee.com",
    "theme_support_url": "https://www.onehalfcoffee.com"
  },
  {
    "name": "Colors",
    "settings": [
      {
        "type": "color",
        "id": "background",
        "label": "Background Color",
        "default": "#FAF9F6"
      },
      {
        "type": "color",
        "id": "text",
        "label": "Text Color",
        "default": "#171717"
      },
      {
        "type": "color",
        "id": "accent",
        "label": "Accent Color (Amber/Brown)",
        "default": "#D97706"
      }
    ]
  },
  {
    "name": "Typography",
    "settings": [
      {
        "type": "font_picker",
        "id": "heading_font",
        "label": "Heading Font",
        "default": "serif"
      },
      {
        "type": "font_picker",
        "id": "body_font",
        "label": "Body Font",
        "default": "sans-serif"
      }
    ]
  }
]
